hatyan/__init__.py
hatyan/analysis_prediction.py
hatyan/astrog.py
hatyan/cli.py
hatyan/components.py
hatyan/ddlpy_helpers.py
hatyan/deprecated.py
hatyan/foreman.py
hatyan/hatyan_core.py
hatyan/metadata.py
hatyan/schureman.py
hatyan/timeseries.py
hatyan/utils.py
hatyan/data/data_M2phasediff_perstation.txt
hatyan/data/data_foreman_frequencies.txt
hatyan/data/data_foreman_harmonic.txt
hatyan/data/data_foreman_shallowrelations.txt
hatyan/data/data_schureman_harmonic.csv
hatyan/data/data_schureman_shallowrelations.csv
hatyan/data/leap-seconds.list
hatyan-2.13.0.dist-info/licenses/LICENSE
hatyan-2.13.0.dist-info/licenses/LICENSE.LESSER
hatyan-2.13.0.dist-info/METADATA
hatyan-2.13.0.dist-info/WHEEL
hatyan-2.13.0.dist-info/entry_points.txt
hatyan-2.13.0.dist-info/top_level.txt
hatyan-2.13.0.dist-info/RECORD
