Metadata-Version: 2.4
Name: hatyan
Version: 2.13.0
Summary: Tidal analysis and prediction tool of Rijkswaterstaat
Maintainer-email: Jelmer Veenstra <jelmer.veenstra@deltares.nl>
License-Expression: LGPL-3.0
Project-URL: Home, https://github.com/deltares/hatyan
Project-URL: Code, https://github.com/deltares/hatyan
Project-URL: Issues, https://github.com/deltares/hatyan/issues
Keywords: hatyan,tidal analysis,tidal prediction
Classifier: Development Status :: 5 - Production/Stable
Classifier: Intended Audience :: Science/Research
Classifier: Operating System :: OS Independent
Classifier: Topic :: Scientific/Engineering :: Information Analysis
Classifier: Programming Language :: Python
Classifier: Programming Language :: Python :: 3
Classifier: Programming Language :: Python :: 3.9
Classifier: Programming Language :: Python :: 3.10
Classifier: Programming Language :: Python :: 3.11
Classifier: Programming Language :: Python :: 3.12
Classifier: Programming Language :: Python :: 3.13
Classifier: Programming Language :: Python :: 3.14
Requires-Python: >=3.9
License-File: LICENSE
License-File: LICENSE.LESSER
Requires-Dist: scipy>=1.5.4
Requires-Dist: numpy>=1.24.0
Requires-Dist: matplotlib>=3.7.0
Requires-Dist: pandas>=2.1.0
Requires-Dist: netcdf4>=1.5.6
Requires-Dist: pyproj>=3.1.0
Requires-Dist: requests>=2.28.0
Requires-Dist: xarray>=2023.4.0
Requires-Dist: rws-ddlpy>=0.8.0
Requires-Dist: click>=7.1
Provides-Extra: dev
Requires-Dist: bump2version>=0.5.11; extra == "dev"
Requires-Dist: flake8; extra == "dev"
Requires-Dist: pytest; extra == "dev"
Requires-Dist: pytest-cov; extra == "dev"
Requires-Dist: twine; extra == "dev"
Requires-Dist: build; extra == "dev"
Provides-Extra: docs
Requires-Dist: sphinx>=1.8.1; extra == "docs"
Requires-Dist: sphinx_mdinclude; extra == "docs"
Requires-Dist: nbsphinx; extra == "docs"
Requires-Dist: pydata-sphinx-theme; extra == "docs"
Provides-Extra: examples
Requires-Dist: jupyter; extra == "examples"
Requires-Dist: notebook; extra == "examples"
Dynamic: license-file
